modules/__init__.py
modules/module.py
pypi_test_carrie5-2.0.0.dist-info/LICENSE.txt
pypi_test_carrie5-2.0.0.dist-info/METADATA
pypi_test_carrie5-2.0.0.dist-info/WHEEL
pypi_test_carrie5-2.0.0.dist-info/top_level.txt
pypi_test_carrie5-2.0.0.dist-info/RECORD
