Metadata-Version: 2.1
Name: pypi_test_carrie5
Version: 2.0.0
Summary: pypi测试
Home-page: https://github.com/test
Author: carrie
Author-email: 123456789@qq.com
License: MIT
Platform: UNKNOWN
Classifier: License :: OSI Approved :: MIT License
Classifier: Operating System :: OS Independent
Classifier: Programming Language :: Python :: 3
Requires-Python: >=3.6
License-File: LICENSE.txt
Requires-Dist: pandas==1.3.5
